starpack/__init__.py
starpack/__main__.py
starpack/_config.py
starpack/client.py
starpack/core.py
starpack/errors.py
starpack/initialize.py
starpack/utils.py
starpack/templates/predict.py
starpack/templates/requirements.txt
starpack/templates/starpack.yaml
starpack/testing/__init__.py
tests/__init__.py
tests/test_commands.py
tests/test_core.py
tests/test_engine_client.py
tests/test_errors.py
starpack-0.2.1.dist-info/LICENSE
starpack-0.2.1.dist-info/METADATA
starpack-0.2.1.dist-info/WHEEL
starpack-0.2.1.dist-info/entry_points.txt
starpack-0.2.1.dist-info/top_level.txt
starpack-0.2.1.dist-info/RECORD
