Metadata-Version: 2.1
Name: starpack
Version: 0.2.1
Summary: A modular utility to package and deploy ML models
Author: "Andromeda 360, Inc"
Author-email: irvin.shen@andromeda360.ai
License: Apache License Version 2.0
Keywords: Swagger,OpenAPI,ModelOps,CLI,DataScience,DevOps,MLOps
Classifier: Topic :: Utilities
Classifier: Intended Audience :: Developers
Classifier: Intended Audience :: End Users/Desktop
Classifier: Intended Audience :: Information Technology
Classifier: Intended Audience :: Science/Research
Classifier: License :: OSI Approved :: Apache Software License
Classifier: Operating System :: OS Independent
Classifier: Programming Language :: Python
Classifier: Programming Language :: Python :: 3.7
Classifier: Programming Language :: Python :: 3.8
Classifier: Programming Language :: Python :: 3.9
Classifier: Programming Language :: Python :: 3.10
License-File: LICENSE
Requires-Dist: typer[all] (<1.0.0,>=0.6.1)
Requires-Dist: docker (<7.0.0,>=6.0.0)
Requires-Dist: requests (<3.0.0,>=2.28.1)
Requires-Dist: pydantic[dotenv] (<1.11.0,>=1.10.2)
Requires-Dist: PyYAML (<7.0,>=6.0)
Requires-Dist: click (>=8.0.0) ; platform_system == "Windows"
Provides-Extra: dev
Requires-Dist: pytest (<=8.0.0,>=7.1.2) ; extra == 'dev'
Requires-Dist: pytest-cov (<=4.0.0,>=3.0.0) ; extra == 'dev'
Requires-Dist: requests-mock (<=1.11.0,>=1.10.0) ; extra == 'dev'
Requires-Dist: black (>=22.0.0) ; extra == 'dev'
